insurancespellcheck/__init__.py
insurancespell-0.2.dist-info/METADATA
insurancespell-0.2.dist-info/WHEEL
insurancespell-0.2.dist-info/top_level.txt
insurancespell-0.2.dist-info/RECORD
