Metadata-Version: 2.1
Name: insurancespell
Version: 0.2
Summary: Thai insurance Spell Check
Home-page: https://github.com/Thiraphat-DEV/Insurance-Spell
Author: Thiraphat Chorakhe
Author-email: thiraboaty@gmail.com
License: Apache Software License 2.0
Keywords: insurance
Classifier: Development Status :: 3 - Alpha
Classifier: Intended Audience :: Developers
Classifier: License :: OSI Approved :: Apache Software License
Classifier: Programming Language :: Python :: Implementation
Requires-Dist: pythainlp >=3.10
Requires-Dist: sklearn-crfsuite
